giteapy/__init__.py
giteapy/api_client.py
giteapy/configuration.py
giteapy/rest.py
giteapy/api/__init__.py
giteapy/api/admin_api.py
giteapy/api/issue_api.py
giteapy/api/miscellaneous_api.py
giteapy/api/notification_api.py
giteapy/api/organization_api.py
giteapy/api/repository_api.py
giteapy/api/settings_api.py
giteapy/api/user_api.py
giteapy/models/__init__.py
giteapy/models/access_token.py
giteapy/models/add_collaborator_option.py
giteapy/models/add_time_option.py
giteapy/models/annotated_tag.py
giteapy/models/annotated_tag_object.py
giteapy/models/api_error.py
giteapy/models/attachment.py
giteapy/models/branch.py
giteapy/models/branch_protection.py
giteapy/models/combined_status.py
giteapy/models/comment.py
giteapy/models/commit.py
giteapy/models/commit_affected_files.py
giteapy/models/commit_date_options.py
giteapy/models/commit_meta.py
giteapy/models/commit_status.py
giteapy/models/commit_status_state.py
giteapy/models/commit_user.py
giteapy/models/contents_response.py
giteapy/models/create_branch_protection_option.py
giteapy/models/create_branch_repo_option.py
giteapy/models/create_email_option.py
giteapy/models/create_file_options.py
giteapy/models/create_fork_option.py
giteapy/models/create_gpg_key_option.py
giteapy/models/create_hook_option.py
giteapy/models/create_hook_option_config.py
giteapy/models/create_issue_comment_option.py
giteapy/models/create_issue_option.py
giteapy/models/create_key_option.py
giteapy/models/create_label_option.py
giteapy/models/create_milestone_option.py
giteapy/models/create_o_auth2_application_options.py
giteapy/models/create_org_option.py
giteapy/models/create_pull_request_option.py
giteapy/models/create_pull_review_comment.py
giteapy/models/create_pull_review_options.py
giteapy/models/create_release_option.py
giteapy/models/create_repo_option.py
giteapy/models/create_status_option.py
giteapy/models/create_tag_option.py
giteapy/models/create_team_option.py
giteapy/models/create_user_option.py
giteapy/models/cron.py
giteapy_soteria-1.15.0.dist-info/METADATA
giteapy_soteria-1.15.0.dist-info/WHEEL
giteapy_soteria-1.15.0.dist-info/top_level.txt
giteapy_soteria-1.15.0.dist-info/RECORD
