Metadata-Version: 2.1
Name: giteapy-soteria
Version: 1.15.0
Summary: Gitea API.
Home-page: UNKNOWN
Author-email: 
License: UNKNOWN
Keywords: Swagger,Gitea API.
Platform: UNKNOWN
Requires-Dist: certifi (>=2017.4.17)
Requires-Dist: python-dateutil (>=2.1)
Requires-Dist: six (>=1.10)
Requires-Dist: urllib3 (>=1.23)
